MemoryReadFSM.v
module MemoryReadFSM (
    input clk,             // سیگنال ساعت
    input reset,           // سیگنال ریست
    input [1:0] Op,        // نوع دستور (برای تشخیص عملیات Memory Read)
    input Func,            // تابع برای شناسایی دستور LDR
    output reg AdrSrc,     // کنترل انتخاب آدرس
    output reg ALUSrcA,    // ورودی اول ALU
    output reg [1:0] ALUSrcB, // ورودی دوم ALU
    output reg [1:0] ALUOp,   // نوع عملیات ALU
    output reg [1:0] ResultSrc, // کنترل انتخاب نتیجه
    output reg IRWrite,    // سیگنال نوشتن در رجیستر دستور
    output reg NextPC,     // سیگنال برای به‌روز‌رسانی PC
    output reg RegWrite,   // سیگنال نوشتن در رجیستر
    output reg MemRead     // سیگنال خواندن از حافظه
);

    // تعریف حالت‌ها به صورت مقادیر ثابت
    localparam FETCH    = 3'b000;  // S0: Fetch
    localparam DECODE   = 3'b001;  // S1: Decode
    localparam MEM_ADR  = 3'b010;  // S2: MemAdr
    localparam MEM_READ = 3'b011;  // S3: MemRead
    localparam MEM_WB   = 3'b100;  // S4: MemWB

    reg [2:0] current_state, next_state; // حالت فعلی و بعدی

    // بلاک انتقال وضعیت‌ها
    always @(posedge clk or posedge reset) begin
        if (reset)
            current_state <= FETCH; // بازگشت به حالت Fetch در صورت ریست
        else
            current_state <= next_state; // انتقال به حالت بعدی
    end

    // منطق انتقال بین وضعیت‌ها
    always @(*) begin
        // مقدار پیش‌فرض برای جلوگیری از خطا
        next_state = current_state;
        case (current_state)
            FETCH: 
                next_state = DECODE; // انتقال به Decode
            DECODE: 
                if (Op == 2'b01) // اگر دستور Memory Read باشد
                    next_state = MEM_ADR;
                else
                    next_state = FETCH;
            MEM_ADR: 
                next_state = MEM_READ; // انتقال به حالت خواندن حافظه
            MEM_READ: 
                next_state = MEM_WB; // انتقال به نوشتن در رجیستر
            MEM_WB: 
                next_state = FETCH; // بازگشت به Fetch برای دستور بعدی
        endcase
    end

    // منطق خروجی بر اساس وضعیت فعلی
    always @(*) begin
        // مقداردهی پیش‌فرض به سیگنال‌ها
        AdrSrc = 0; ALUSrcA = 0; ALUSrcB = 2'b00; ALUOp = 2'b00; 
        ResultSrc = 2'b00; IRWrite = 0; NextPC = 0; RegWrite = 0; MemRead = 0;

        case (current_state)
            FETCH: begin
                AdrSrc = 0;
                ALUSrcA = 1;
                ALUSrcB = 2'b10;
                ALUOp = 2'b00;
                ResultSrc = 2'b10;
                IRWrite = 1;
                NextPC = 1;
            end
            DECODE: begin
                ALUSrcA = 1;
                ALUSrcB = 2'b10;
                ALUOp = 2'b00;
                ResultSrc = 2'b10;
            end
            MEM_ADR: begin
                ALUSrcA = 0;
                ALUSrcB = 2'b01;
                ALUOp = 2'b00;
            end
            MEM_READ: begin
                MemRead = 1;
                AdrSrc = 1;
                ResultSrc = 2'b00;
            end
            MEM_WB: begin
                ResultSrc = 2'b01;
                RegWrite = 1;
            end
        endcase
    end

endmodule

MemoryReadFSM_tb.v
`timescale 1ns / 1ps

module MemoryReadFSM_tb;

    // Input declarations
    reg clk;
    reg reset;
    reg [1:0] Op;
    reg Func;

    // Output declarations
    wire AdrSrc;
    wire ALUSrcA;
    wire [1:0] ALUSrcB;
    wire [1:0] ALUOp;
    wire [1:0] ResultSrc;
    wire IRWrite;
    wire NextPC;
    wire RegWrite;
    wire MemRead;

    // Instantiate the MemoryReadFSM module
    MemoryReadFSM uut (
        .clk(clk),
        .reset(reset),
        .Op(Op),
        .Func(Func),
        .AdrSrc(AdrSrc),
        .ALUSrcA(ALUSrcA),
        .ALUSrcB(ALUSrcB),
        .ALUOp(ALUOp),
        .ResultSrc(ResultSrc),
        .IRWrite(IRWrite),
        .NextPC(NextPC),
        .RegWrite(RegWrite),
        .MemRead(MemRead)
    );

    // Clock generation (10ns period)
    always #5 clk = ~clk;

    // Initial block to set up the test and produce VCD output
    initial begin
        // Set up VCD file for waveform visualization
        $dumpfile("MemoryReadFSM_tb.vcd");  // Specify VCD file name
        $dumpvars(0, MemoryReadFSM_tb);     // Dump all variables for the testbench

        // Initialization
        clk = 0;
        reset = 1;
        Op = 2'b00;
        Func = 0;

        // Apply reset
        #10 reset = 0;

        // Apply test cases
        #10 Op = 2'b01; // Memory Read instruction
        Func = 1;       // LDR instruction

        #20;  // Wait for next state transition
        #20;  // Continue simulation

        // Finish simulation
        #50 $stop;
    end

endmodule

MemoryReadFSM_tb.vcd
$date
	Wed Dec 04 16:08:38 2024
$end
$version
	Icarus Verilog
$end
$timescale
	1ps
$end
$scope module MemoryReadFSM_tb $end
$var wire 2 ! ResultSrc [1:0] $end
$var wire 1 " RegWrite $end
$var wire 1 # NextPC $end
$var wire 1 $ MemRead $end
$var wire 1 % IRWrite $end
$var wire 1 & AdrSrc $end
$var wire 2 ' ALUSrcB [1:0] $end
$var wire 1 ( ALUSrcA $end
$var wire 2 ) ALUOp [1:0] $end
$var reg 1 * Func $end
$var reg 2 + Op [1:0] $end
$var reg 1 , clk $end
$var reg 1 - reset $end
$scope module uut $end
$var wire 1 * Func $end
$var wire 2 . Op [1:0] $end
$var wire 1 , clk $end
$var wire 1 - reset $end
$var parameter 3 / DECODE $end
$var parameter 3 0 FETCH $end
$var parameter 3 1 MEM_ADR $end
$var parameter 3 2 MEM_READ $end
$var parameter 3 3 MEM_WB $end
$var reg 2 4 ALUOp [1:0] $end
$var reg 1 ( ALUSrcA $end
$var reg 2 5 ALUSrcB [1:0] $end
$var reg 1 & AdrSrc $end
$var reg 1 % IRWrite $end
$var reg 1 $ MemRead $end
$var reg 1 # NextPC $end
$var reg 1 " RegWrite $end
$var reg 2 6 ResultSrc [1:0] $end
$var reg 3 7 current_state [2:0] $end
$var reg 3 8 next_state [2:0] $end
$upscope $end
$upscope $end
$enddefinitions $end
$comment Show the parameter values. $end
$dumpall
b100 3
b11 2
b10 1
b0 0
b1 /
$end
#0
$dumpvars
b1 8
b0 7
b10 6
b10 5
b0 4
b0 .
1-
0,
b0 +
0*
b0 )
1(
b10 '
0&
1%
0$
1#
0"
b10 !
$end
#5000
1,
#10000
0,
0-
#15000
0#
0%
b10 !
b10 6
b10 '
b10 5
1(
b0 8
b1 7
1,
#20000
b10 8
0,
1*
b1 +
b1 .
#25000
b0 !
b0 6
b1 '
b1 5
0(
b11 8
b10 7
1,
#30000
0,
#35000
1&
1$
b0 '
b0 5
b100 8
b11 7
1,
#40000
0,
#45000
1"
b1 !
b1 6
0$
0&
b0 8
b100 7
1,
#50000
0,
#55000
1#
1%
b10 '
b10 5
1(
0"
b10 !
b10 6
b1 8
b0 7
1,
#60000
0,
#65000
0#
0%
b10 !
b10 6
b10 '
b10 5
1(
b10 8
b1 7
1,
#70000
0,
#75000
b0 !
b0 6
b1 '
b1 5
0(
b11 8
b10 7
1,
#80000
0,
#85000
1&
1$
b0 '
b0 5
b100 8
b11 7
1,
#90000
0,
#95000
1"
b1 !
b1 6
0$
0&
b0 8
b100 7
1,
#100000
0,
#105000
1#
1%
b10 '
b10 5
1(
0"
b10 !
b10 6
b1 8
b0 7
1,
